geomock/__init__.py
geomock/cli.py
geomock/mappable_feature.py
geomock/ops.py
geomock/random_feature.py
geomock/random_geometry.py
geomock/util.py
geomock-2.0.1.dist-info/entry_points.txt
geomock-2.0.1.dist-info/LICENSE
geomock-2.0.1.dist-info/WHEEL
geomock-2.0.1.dist-info/METADATA
geomock-2.0.1.dist-info/RECORD
